[{"username":"root","content":"hello","time":"2026/6/18 18:44:38"},{"username":"root","content":"hello","time":"2026/6/18 19:28:39"},{"username":"root","content":"oi","time":"2026/6/19 13:44:42"},{"username":"gyy-root","content":"oi","time":"2026/6/19 13:47:09"},{"username":"root","content":"gama","time":"2026/6/19 13:47:23"},{"username":"root","content":"cs","time":"2026/6/19 13:48:34"},{"username":"root","content":"cs","time":"2026/6/19 13:48:35"},{"username":"root","content":"cs","time":"2026/6/19 13:48:36"},{"username":"root","content":"cs","time":"2026/6/19 13:48:44"},{"username":"root","content":"在吗","time":"2026/6/19 13:52:22"},{"username":"gyy-root","content":"在","time":"2026/6/19 16:07:18"}]